{
  "data_root": "/cluster/scratch/ppurkayastha/Acads/SCAI/asia2026_starter/data/staged",
  "device": "cuda",
  "method": "t1_saits_pypots_cv",
  "n_splits": 3,
  "notes": "",
  "oof_breakdown": {
    "per_target": {
      "anyana": {
        "mae": 0.04136760160326958,
        "n": 158.0,
        "r2": -0.4245786666870117,
        "rmse": 0.1334330439567566,
        "sensory": false
      },
      "c2ltl": {
        "mae": 0.682723879814148,
        "n": 314.0,
        "r2": 0.0,
        "rmse": 0.8991222977638245,
        "sensory": true
      },
      "c2ltr": {
        "mae": 0.13602134585380554,
        "n": 52.0,
        "r2": 0.0,
        "rmse": 0.21118955314159393,
        "sensory": true
      },
      "c2ppl": {
        "mae": 0.7977054715156555,
        "n": 358.0,
        "r2": -237.4803466796875,
        "rmse": 0.8150371313095093,
        "sensory": true
      },
      "c2ppr": {
        "mae": 1.138890027999878,
        "n": 369.0,
        "r2": -515.3148193359375,
        "rmse": 1.1812852621078491,
        "sensory": true
      },
      "c3ltl": {
        "mae": 0.6192192435264587,
        "n": 249.0,
        "r2": -17.658233642578125,
        "rmse": 0.8593561053276062,
        "sensory": true
      },
      "c3ltr": {
        "mae": 0.16022683680057526,
        "n": 43.0,
        "r2": -0.20965099334716797,
        "rmse": 0.33152496814727783,
        "sensory": true
      },
      "c3ppl": {
        "mae": 0.7766069769859314,
        "n": 287.0,
        "r2": -12.378324508666992,
        "rmse": 0.797721266746521,
        "sensory": true
      },
      "c3ppr": {
        "mae": 1.0970135927200317,
        "n": 292.0,
        "r2": -37.674346923828125,
        "rmse": 1.1381715536117554,
        "sensory": true
      },
      "c4ltl": {
        "mae": 0.629083514213562,
        "n": 178.0,
        "r2": -4.630608081817627,
        "rmse": 0.8959477543830872,
        "sensory": true
      },
      "c4ltr": {
        "mae": 0.4551442265510559,
        "n": 38.0,
        "r2": -0.1316167116165161,
        "rmse": 0.7490703463554382,
        "sensory": true
      },
      "c4ppl": {
        "mae": 0.7998263835906982,
        "n": 204.0,
        "r2": -2.025470495223999,
        "rmse": 0.8401003479957581,
        "sensory": true
      },
      "c4ppr": {
        "mae": 1.0658633708953857,
        "n": 199.0,
        "r2": -7.362048149108887,
        "rmse": 1.1074306964874268,
        "sensory": true
      },
      "c5ltl": {
        "mae": 0.6965575218200684,
        "n": 224.0,
        "r2": -0.6784706115722656,
        "rmse": 0.9476161599159241,
        "sensory": true
      },
      "c5ltr": {
        "mae": 0.9026648998260498,
        "n": 88.0,
        "r2": -0.7784481048583984,
        "rmse": 1.1687548160552979,
        "sensory": true
      },
      "c5ppl": {
        "mae": 0.8591907620429993,
        "n": 237.0,
        "r2": -0.22266829013824463,
        "rmse": 0.929985523223877,
        "sensory": true
      },
      "c5ppr": {
        "mae": 0.9615138173103333,
        "n": 217.0,
        "r2": -0.5806699991226196,
        "rmse": 1.0247268676757812,
        "sensory": true
      },
      "c6ltl": {
        "mae": 0.7974025011062622,
        "n": 322.0,
        "r2": -0.5399734973907471,
        "rmse": 1.0355172157287598,
        "sensory": true
      },
      "c6ltr": {
        "mae": 0.8270101547241211,
        "n": 228.0,
        "r2": -0.6102052927017212,
        "rmse": 1.0769389867782593,
        "sensory": true
      },
      "c6ppl": {
        "mae": 0.8858498930931091,
        "n": 327.0,
        "r2": -0.13884055614471436,
        "rmse": 0.9650144577026367,
        "sensory": true
      },
      "c6ppr": {
        "mae": 0.9431582093238831,
        "n": 330.0,
        "r2": -0.30117011070251465,
        "rmse": 1.0148849487304688,
        "sensory": true
      },
      "c7ltl": {
        "mae": 0.8641168475151062,
        "n": 367.0,
        "r2": -0.4812663793563843,
        "rmse": 1.0781413316726685,
        "sensory": true
      },
      "c7ltr": {
        "mae": 0.9341757297515869,
        "n": 282.0,
        "r2": -0.8295743465423584,
        "rmse": 1.1755379438400269,
        "sensory": true
      },
      "c7ppl": {
        "mae": 0.8808243870735168,
        "n": 373.0,
        "r2": -0.10440969467163086,
        "rmse": 0.9735096096992493,
        "sensory": true
      },
      "c7ppr": {
        "mae": 0.9342198371887207,
        "n": 374.0,
        "r2": -0.22465944290161133,
        "rmse": 1.028030276298523,
        "sensory": true
      },
      "c8ltl": {
        "mae": 0.9135209918022156,
        "n": 374.0,
        "r2": -0.4856724739074707,
        "rmse": 1.1008086204528809,
        "sensory": true
      },
      "c8ltr": {
        "mae": 1.082309603691101,
        "n": 299.0,
        "r2": -1.2304320335388184,
        "rmse": 1.3106915950775146,
        "sensory": true
      },
      "c8ppl": {
        "mae": 0.8686336278915405,
        "n": 375.0,
        "r2": -0.06315779685974121,
        "rmse": 0.9553225636482239,
        "sensory": true
      },
      "c8ppr": {
        "mae": 0.9324141144752502,
        "n": 380.0,
        "r2": -0.23366165161132812,
        "rmse": 1.0379352569580078,
        "sensory": true
      },
      "l1ltl": {
        "mae": 1.0848228931427002,
        "n": 398.0,
        "r2": -2.0800130367279053,
        "rmse": 1.2558521032333374,
        "sensory": true
      },
      "l1ltr": {
        "mae": 1.3498049974441528,
        "n": 395.0,
        "r2": -3.436939239501953,
        "rmse": 1.4694769382476807,
        "sensory": true
      },
      "l1ppl": {
        "mae": 0.8286404013633728,
        "n": 398.0,
        "r2": -1.0790815353393555,
        "rmse": 0.9269237518310547,
        "sensory": true
      },
      "l1ppr": {
        "mae": 0.7992406487464905,
        "n": 398.0,
        "r2": -1.0932002067565918,
        "rmse": 0.8803068995475769,
        "sensory": true
      },
      "l2ltl": {
        "mae": 1.0739582777023315,
        "n": 399.0,
        "r2": -1.9341778755187988,
        "rmse": 1.2441233396530151,
        "sensory": true
      },
      "l2ltr": {
        "mae": 1.370926022529602,
        "n": 396.0,
        "r2": -3.5425920486450195,
        "rmse": 1.4892936944961548,
        "sensory": true
      },
      "l2ppl": {
        "mae": 0.8047226667404175,
        "n": 399.0,
        "r2": -0.9234529733657837,
        "rmse": 0.8999037146568298,
        "sensory": true
      },
      "l2ppr": {
        "mae": 0.7835996150970459,
        "n": 399.0,
        "r2": -1.0421977043151855,
        "rmse": 0.860178530216217,
        "sensory": true
      },
      "l3ltl": {
        "mae": 1.0663892030715942,
        "n": 400.0,
        "r2": -1.7235383987426758,
        "rmse": 1.2286187410354614,
        "sensory": true
      },
      "l3ltr": {
        "mae": 1.3455424308776855,
        "n": 398.0,
        "r2": -3.0902910232543945,
        "rmse": 1.4696767330169678,
        "sensory": true
      },
      "l3ppl": {
        "mae": 0.8040998578071594,
        "n": 400.0,
        "r2": -1.0582151412963867,
        "rmse": 0.8924560546875,
        "sensory": true
      },
      "l3ppr": {
        "mae": 0.7825944423675537,
        "n": 400.0,
        "r2": -0.9432319402694702,
        "rmse": 0.8522508144378662,
        "sensory": true
      },
      "l4ltl": {
        "mae": 1.0731772184371948,
        "n": 400.0,
        "r2": -1.713888168334961,
        "rmse": 1.2252780199050903,
        "sensory": true
      },
      "l4ltr": {
        "mae": 1.3319315910339355,
        "n": 398.0,
        "r2": -3.0617899894714355,
        "rmse": 1.4579582214355469,
        "sensory": true
      },
      "l4ppl": {
        "mae": 0.8354951739311218,
        "n": 400.0,
        "r2": -1.0428812503814697,
        "rmse": 0.9170830845832825,
        "sensory": true
      },
      "l4ppr": {
        "mae": 0.7839745879173279,
        "n": 400.0,
        "r2": -0.8934024572372437,
        "rmse": 0.855944037437439,
        "sensory": true
      },
      "l5ltl": {
        "mae": 1.064613699913025,
        "n": 400.0,
        "r2": -1.5788118839263916,
        "rmse": 1.2117388248443604,
        "sensory": true
      },
      "l5ltr": {
        "mae": 1.294606328010559,
        "n": 398.0,
        "r2": -2.554027795791626,
        "rmse": 1.4251139163970947,
        "sensory": true
      },
      "l5ppl": {
        "mae": 0.8764100670814514,
        "n": 400.0,
        "r2": -1.1925475597381592,
        "rmse": 0.9568740129470825,
        "sensory": true
      },
      "l5ppr": {
        "mae": 0.7821850776672363,
        "n": 400.0,
        "r2": -0.892004132270813,
        "rmse": 0.8600940704345703,
        "sensory": true
      },
      "s1ltl": {
        "mae": 1.0287196636199951,
        "n": 400.0,
        "r2": -1.3715429306030273,
        "rmse": 1.1777585744857788,
        "sensory": true
      },
      "s1ltr": {
        "mae": 1.2927277088165283,
        "n": 398.0,
        "r2": -2.5695700645446777,
        "rmse": 1.4217429161071777,
        "sensory": true
      },
      "s1ppl": {
        "mae": 0.8998615741729736,
        "n": 400.0,
        "r2": -1.0283477306365967,
        "rmse": 0.9782247543334961,
        "sensory": true
      },
      "s1ppr": {
        "mae": 0.7848331928253174,
        "n": 400.0,
        "r2": -0.7447209358215332,
        "rmse": 0.8637375831604004,
        "sensory": true
      },
      "s2ltl": {
        "mae": 0.9965461492538452,
        "n": 400.0,
        "r2": -1.1066830158233643,
        "rmse": 1.1470983028411865,
        "sensory": true
      },
      "s2ltr": {
        "mae": 1.2993770837783813,
        "n": 398.0,
        "r2": -2.731908082962036,
        "rmse": 1.4275553226470947,
        "sensory": true
      },
      "s2ppl": {
        "mae": 0.9127975702285767,
        "n": 400.0,
        "r2": -1.110396385192871,
        "rmse": 0.9817892909049988,
        "sensory": true
      },
      "s2ppr": {
        "mae": 0.7725858092308044,
        "n": 400.0,
        "r2": -0.8363202810287476,
        "rmse": 0.8591594099998474,
        "sensory": true
      },
      "s3ltl": {
        "mae": 0.943339467048645,
        "n": 398.0,
        "r2": -0.9473930597305298,
        "rmse": 1.0982197523117065,
        "sensory": true
      },
      "s3ltr": {
        "mae": 1.2665386199951172,
        "n": 398.0,
        "r2": -2.351799249649048,
        "rmse": 1.4118342399597168,
        "sensory": true
      },
      "s3ppl": {
        "mae": 0.8779644966125488,
        "n": 398.0,
        "r2": -0.8285893201828003,
        "rmse": 0.9534733295440674,
        "sensory": true
      },
      "s3ppr": {
        "mae": 0.7635671496391296,
        "n": 398.0,
        "r2": -0.5790002346038818,
        "rmse": 0.8675527572631836,
        "sensory": true
      },
      "s45ltl": {
        "mae": 0.7382848858833313,
        "n": 150.0,
        "r2": -1.6761610507965088,
        "rmse": 0.8792685866355896,
        "sensory": true
      },
      "s45ppl": {
        "mae": 0.6869794130325317,
        "n": 153.0,
        "r2": -0.037273406982421875,
        "rmse": 0.8013447523117065,
        "sensory": true
      },
      "s45ppr": {
        "mae": 0.7458323836326599,
        "n": 153.0,
        "r2": -0.303641676902771,
        "rmse": 0.8996638655662537,
        "sensory": true
      },
      "t10ltl": {
        "mae": 0.9927170276641846,
        "n": 395.0,
        "r2": -1.0859637260437012,
        "rmse": 1.1216099262237549,
        "sensory": true
      },
      "t10ltr": {
        "mae": 1.323305368423462,
        "n": 380.0,
        "r2": -2.9009504318237305,
        "rmse": 1.4503405094146729,
        "sensory": true
      },
      "t10ppl": {
        "mae": 0.8826084136962891,
        "n": 394.0,
        "r2": -0.89715576171875,
        "rmse": 0.9687281847000122,
        "sensory": true
      },
      "t10ppr": {
        "mae": 0.8183472156524658,
        "n": 391.0,
        "r2": -0.9942629337310791,
        "rmse": 0.9100825190544128,
        "sensory": true
      },
      "t11ltl": {
        "mae": 1.0248769521713257,
        "n": 399.0,
        "r2": -1.4517111778259277,
        "rmse": 1.1722679138183594,
        "sensory": true
      },
      "t11ltr": {
        "mae": 1.3604156970977783,
        "n": 388.0,
        "r2": -3.4871153831481934,
        "rmse": 1.4794304370880127,
        "sensory": true
      },
      "t11ppl": {
        "mae": 0.8879015445709229,
        "n": 399.0,
        "r2": -0.9952139854431152,
        "rmse": 0.9819948673248291,
        "sensory": true
      },
      "t11ppr": {
        "mae": 0.828605055809021,
        "n": 398.0,
        "r2": -1.103466510772705,
        "rmse": 0.9130589962005615,
        "sensory": true
      },
      "t12ltl": {
        "mae": 1.0648494958877563,
        "n": 399.0,
        "r2": -2.1019630432128906,
        "rmse": 1.2262552976608276,
        "sensory": true
      },
      "t12ltr": {
        "mae": 1.3515533208847046,
        "n": 394.0,
        "r2": -3.4845428466796875,
        "rmse": 1.470193862915039,
        "sensory": true
      },
      "t12ppl": {
        "mae": 0.8773485422134399,
        "n": 398.0,
        "r2": -1.1411168575286865,
        "rmse": 0.9754914045333862,
        "sensory": true
      },
      "t12ppr": {
        "mae": 0.8191442489624023,
        "n": 398.0,
        "r2": -1.167400598526001,
        "rmse": 0.9018325805664062,
        "sensory": true
      },
      "t1ltl": {
        "mae": 0.8717314600944519,
        "n": 379.0,
        "r2": -0.38734889030456543,
        "rmse": 1.0439538955688477,
        "sensory": true
      },
      "t1ltr": {
        "mae": 1.0145188570022583,
        "n": 308.0,
        "r2": -1.0714616775512695,
        "rmse": 1.2617212533950806,
        "sensory": true
      },
      "t1ppl": {
        "mae": 0.8766562938690186,
        "n": 381.0,
        "r2": -0.04009413719177246,
        "rmse": 0.9476073980331421,
        "sensory": true
      },
      "t1ppr": {
        "mae": 0.9338847994804382,
        "n": 384.0,
        "r2": -0.2378523349761963,
        "rmse": 1.031250238418579,
        "sensory": true
      },
      "t2ltl": {
        "mae": 0.8756108283996582,
        "n": 381.0,
        "r2": -0.35166311264038086,
        "rmse": 1.0464988946914673,
        "sensory": true
      },
      "t2ltr": {
        "mae": 1.0348507165908813,
        "n": 317.0,
        "r2": -1.1039557456970215,
        "rmse": 1.2885982990264893,
        "sensory": true
      },
      "t2ppl": {
        "mae": 0.8674523234367371,
        "n": 385.0,
        "r2": 0.013477623462677002,
        "rmse": 0.9264678955078125,
        "sensory": true
      },
      "t2ppr": {
        "mae": 0.9125663638114929,
        "n": 383.0,
        "r2": -0.140633225440979,
        "rmse": 1.0017204284667969,
        "sensory": true
      },
      "t3ltl": {
        "mae": 0.8919994235038757,
        "n": 370.0,
        "r2": -0.4303865432739258,
        "rmse": 1.0733122825622559,
        "sensory": true
      },
      "t3ltr": {
        "mae": 1.0928188562393188,
        "n": 317.0,
        "r2": -1.2812144756317139,
        "rmse": 1.3254072666168213,
        "sensory": true
      },
      "t3ppl": {
        "mae": 0.8774327039718628,
        "n": 371.0,
        "r2": -0.020383000373840332,
        "rmse": 0.9326440691947937,
        "sensory": true
      },
      "t3ppr": {
        "mae": 0.8971638679504395,
        "n": 370.0,
        "r2": -0.07618892192840576,
        "rmse": 0.967138409614563,
        "sensory": true
      },
      "t4ltl": {
        "mae": 0.9404749274253845,
        "n": 371.0,
        "r2": -0.628836989402771,
        "rmse": 1.1292803287506104,
        "sensory": true
      },
      "t4ltr": {
        "mae": 1.161045789718628,
        "n": 322.0,
        "r2": -1.5297460556030273,
        "rmse": 1.3561230897903442,
        "sensory": true
      },
      "t4ppl": {
        "mae": 0.8705424666404724,
        "n": 372.0,
        "r2": -0.10974729061126709,
        "rmse": 0.9354986548423767,
        "sensory": true
      },
      "t4ppr": {
        "mae": 0.8492146134376526,
        "n": 374.0,
        "r2": -0.09947192668914795,
        "rmse": 0.9213663339614868,
        "sensory": true
      },
      "t5ltl": {
        "mae": 0.9711164236068726,
        "n": 380.0,
        "r2": -0.7502410411834717,
        "rmse": 1.1580342054367065,
        "sensory": true
      },
      "t5ltr": {
        "mae": 1.2101454734802246,
        "n": 332.0,
        "r2": -1.8719186782836914,
        "rmse": 1.379710078239441,
        "sensory": true
      },
      "t5ppl": {
        "mae": 0.8686807751655579,
        "n": 380.0,
        "r2": -0.2250990867614746,
        "rmse": 0.9423248767852783,
        "sensory": true
      },
      "t5ppr": {
        "mae": 0.8135634660720825,
        "n": 380.0,
        "r2": -0.16407501697540283,
        "rmse": 0.8954964876174927,
        "sensory": true
      },
      "t6ltl": {
        "mae": 0.9955971837043762,
        "n": 376.0,
        "r2": -0.8652021884918213,
        "rmse": 1.1578090190887451,
        "sensory": true
      },
      "t6ltr": {
        "mae": 1.2454240322113037,
        "n": 346.0,
        "r2": -2.088928699493408,
        "rmse": 1.4045017957687378,
        "sensory": true
      },
      "t6ppl": {
        "mae": 0.8619522452354431,
        "n": 377.0,
        "r2": -0.37210750579833984,
        "rmse": 0.9460235834121704,
        "sensory": true
      },
      "t6ppr": {
        "mae": 0.8035627603530884,
        "n": 379.0,
        "r2": -0.2872447967529297,
        "rmse": 0.8928911685943604,
        "sensory": true
      },
      "t7ltl": {
        "mae": 0.9823750853538513,
        "n": 373.0,
        "r2": -0.9300031661987305,
        "rmse": 1.122928500175476,
        "sensory": true
      },
      "t7ltr": {
        "mae": 1.2852383852005005,
        "n": 356.0,
        "r2": -2.3600351810455322,
        "rmse": 1.4332327842712402,
        "sensory": true
      },
      "t7ppl": {
        "mae": 0.8401529788970947,
        "n": 376.0,
        "r2": -0.4785383939743042,
        "rmse": 0.9255097508430481,
        "sensory": true
      },
      "t7ppr": {
        "mae": 0.7904348969459534,
        "n": 376.0,
        "r2": -0.44627535343170166,
        "rmse": 0.8827625513076782,
        "sensory": true
      },
      "t8ltl": {
        "mae": 0.9881004095077515,
        "n": 381.0,
        "r2": -0.9284013509750366,
        "rmse": 1.111992597579956,
        "sensory": true
      },
      "t8ltr": {
        "mae": 1.3016406297683716,
        "n": 365.0,
        "r2": -2.624140739440918,
        "rmse": 1.4401658773422241,
        "sensory": true
      },
      "t8ppl": {
        "mae": 0.8500405550003052,
        "n": 385.0,
        "r2": -0.6185678243637085,
        "rmse": 0.9347450137138367,
        "sensory": true
      },
      "t8ppr": {
        "mae": 0.7766082286834717,
        "n": 382.0,
        "r2": -0.6871747970581055,
        "rmse": 0.8788629770278931,
        "sensory": true
      },
      "t9ltl": {
        "mae": 0.9835003018379211,
        "n": 390.0,
        "r2": -0.9497942924499512,
        "rmse": 1.1039496660232544,
        "sensory": true
      },
      "t9ltr": {
        "mae": 1.3140662908554077,
        "n": 373.0,
        "r2": -2.758514165878296,
        "rmse": 1.4450891017913818,
        "sensory": true
      },
      "t9ppl": {
        "mae": 0.8652107119560242,
        "n": 392.0,
        "r2": -0.7006452083587646,
        "rmse": 0.946086049079895,
        "sensory": true
      },
      "t9ppr": {
        "mae": 0.8067004084587097,
        "n": 384.0,
        "r2": -0.8503856658935547,
        "rmse": 0.9008336663246155,
        "sensory": true
      }
    },
    "per_time": {
      "1": {
        "all": {
          "mae": 1.0378892421722412,
          "n": 10429.0,
          "r2": -1.1672725677490234,
          "rmse": 1.1670763492584229
        },
        "sensory": {
          "mae": 1.0407251119613647,
          "n": 10399.0,
          "r2": -1.1697945594787598,
          "rmse": 1.1687415838241577
        }
      },
      "16": {
        "all": {
          "mae": 0.8790006041526794,
          "n": 8953.0,
          "r2": -0.26291847229003906,
          "rmse": 1.0296341180801392
        },
        "sensory": {
          "mae": 0.883452296257019,
          "n": 8906.0,
          "r2": -0.2629607915878296,
          "rmse": 1.0322906970977783
        }
      },
      "4": {
        "all": {
          "mae": 0.9487358927726746,
          "n": 9449.0,
          "r2": -0.6605758666992188,
          "rmse": 1.089363694190979
        },
        "sensory": {
          "mae": 0.9525550603866577,
          "n": 9410.0,
          "r2": -0.6614444255828857,
          "rmse": 1.0916109085083008
        }
      },
      "8": {
        "all": {
          "mae": 0.940369188785553,
          "n": 9928.0,
          "r2": -0.48332488536834717,
          "rmse": 1.081498384475708
        },
        "sensory": {
          "mae": 0.9441455006599426,
          "n": 9886.0,
          "r2": -0.48372316360473633,
          "rmse": 1.0837377309799194
        }
      }
    }
  },
  "oof_metrics": {
    "mae_all_imputed_only": 0.9544732570648193,
    "mae_sensory_imputed_only": 0.9582107067108154,
    "n_imputed_all": 38759.0,
    "n_imputed_sensory": 38601.0,
    "r2_all_imputed_only": -0.5702846050262451,
    "r2_sensory_imputed_only": -0.5709308385848999,
    "rmse_all_imputed_only": 1.0955760478973389,
    "rmse_sensory_imputed_only": 1.0977827310562134
  },
  "run_id": "t1_saits_pypots_cv__20260223_095953__job58209149__40shpiqh",
  "run_root": "/cluster/scratch/ppurkayastha/Acads/SCAI/asia2026_starter/runs_saits_pypots",
  "saits_config": {
    "attn_dropout": 0.1,
    "batch_size": 128,
    "d_ffn": 128,
    "d_k": 32,
    "d_model": 128,
    "d_v": 32,
    "dropout": 0.1,
    "epochs": 10,
    "n_heads": 4,
    "n_layers": 2,
    "patience": 3
  },
  "saits_input": "sensory_only",
  "seed": 42,
  "smoke": false,
  "test_rows": 16,
  "timestamp": "2026-02-23T09:59:53.431465+00:00",
  "train_rows": 400,
  "val_frac": 0.1
}